[{"Id":"532553252","Name":"Ordinacija 100","Floor":1,"Status":0,"Type":1,"FreeBeds":0},{"Id":"532553255","Name":"Ordinacija 101","Floor":1,"Status":0,"Type":1,"FreeBeds":0},{"Id":"532553257","Name":"Ordinacija 102","Floor":1,"Status":0,"Type":1,"FreeBeds":0},{"Id":"53253252","Name":"Ordinacija 103","Floor":1,"Status":0,"Type":1,"FreeBeds":0},{"Id":"532532528","Name":"Ordinacija 104","Floor":1,"Status":0,"Type":1,"FreeBeds":0},{"Id":"2","Name":"Sala 2","Floor":3,"Status":0,"Type":0,"FreeBeds":0},{"Id":"M2","Name":"Magacin 2","Floor":2,"Status":0,"Type":3,"FreeBeds":0},{"Id":"3","Name":"Sala 3","Floor":3,"Status":0,"Type":0,"FreeBeds":0},{"Id":"3.1","Name":"Sala 3.1","Floor":3,"Status":0,"Type":0,"FreeBeds":0},{"Id":"M1","Name":"Magacin","Floor":0,"Status":0,"Type":3,"FreeBeds":0},{"Id":"53","Name":"Soba za bolnicko leceneje","Floor":2,"Status":0,"Type":2,"FreeBeds":8},{"Id":"4","Name":"Sala 4","Floor":2,"Status":1,"Type":0,"FreeBeds":0},{"Id":"1","Name":"Sala 1","Floor":3,"Status":2,"Type":0,"FreeBeds":0}]